[{
        "_id": "6054284cb6fa33c9cfcd2fab",
        "index": 0,
        "guid": "93bcb599-3098-4c09-b57a-c465d9a370b0",
        "isActive": true,
        "isMatched": true,
        "isMigrated": false,
        "isReturned": true,
        "dateMatched": "Wed Feb 10 2021 16:50:06 GMT+0100 (West Africa Standard Time)",
        "telco": "Ntel",
        "state": "Kebbi",
        "picture": "http://placehold.it/32x32",
        "age": 63,
        "score": 98,
        "eyeColor": "green",
        "name": "Joanne Holloway",
        "gender": "female",
        "phone": "+234 (982) 415-3526",
        "address": "378 Schenck Court, Loveland, Minnesota, 1388"
    },
    {
        "_id": "6054284c0d32071d5583bb79",
        "index": 1,
        "guid": "85441920-6eac-487f-a7b1-90fd576e1741",
        "isActive": false,
        "isMatched": true,
        "isMigrated": true,
        "isReturned": true,
        "dateMatched": "Thu Mar 18 2021 07:46:28 GMT+0100 (West Africa Standard Time)",
        "telco": "Ntel",
        "state": "Plateau",
        "picture": "http://placehold.it/32x32",
        "age": 17,
        "score": 61,
        "eyeColor": "brown",
        "name": "Boyd Green",
        "gender": "male",
        "phone": "+234 (934) 546-3651",
        "address": "963 Bliss Terrace, Belgreen, Palau, 3585"
    },
    {
        "_id": "6054284ca68c78a44c883186",
        "index": 2,
        "guid": "c8920766-b3ec-449c-a42f-b167d6c70b69",
        "isActive": false,
        "isMatched": true,
        "isMigrated": true,
        "isReturned": true,
        "dateMatched": "Fri Jan 15 2021 22:31:43 GMT+0100 (West Africa Standard Time)",
        "telco": "Globacom",
        "state": "Oyo",
        "picture": "http://placehold.it/32x32",
        "age": 21,
        "score": 58,
        "eyeColor": "brown",
        "name": "April Sykes",
        "gender": "female",
        "phone": "+234 (931) 489-2113",
        "address": "910 Varet Street, Hardyville, Arkansas, 7751"
    },
    {
        "_id": "6054284c03d31f43807eb8b7",
        "index": 3,
        "guid": "36fa1cd4-df2f-4fb9-b03b-72f05afefa6e",
        "isActive": true,
        "isMatched": false,
        "isMigrated": true,
        "isReturned": false,
        "dateMatched": "Tue Feb 09 2021 17:58:06 GMT+0100 (West Africa Standard Time)",
        "telco": "nineMobile",
        "state": "Ekiti",
        "picture": "http://placehold.it/32x32",
        "age": 42,
        "score": 74,
        "eyeColor": "brown",
        "name": "Poole Willis",
        "gender": "male",
        "phone": "+234 (829) 438-2883",
        "address": "558 Diamond Street, Cotopaxi, Wisconsin, 5175"
    },
    {
        "_id": "6054284c239ae433ca6ae37f",
        "index": 4,
        "guid": "ae4ad809-2d9c-4c82-ac64-c2693470cf03",
        "isActive": true,
        "isMatched": true,
        "isMigrated": true,
        "isReturned": true,
        "dateMatched": "Wed Feb 24 2021 21:32:04 GMT+0100 (West Africa Standard Time)",
        "telco": "Globacom",
        "state": "Kwara",
        "picture": "http://placehold.it/32x32",
        "age": 33,
        "score": 11,
        "eyeColor": "green",
        "name": "Catherine Stewart",
        "gender": "female",
        "phone": "+234 (934) 595-2109",
        "address": "640 Kansas Place, Smeltertown, Mississippi, 2179"
    },
    {
        "_id": "6054284c10a586545b7445a3",
        "index": 5,
        "guid": "b8b47c94-64a3-4f07-9f28-04dba206c592",
        "isActive": false,
        "isMatched": true,
        "isMigrated": false,
        "isReturned": false,
        "dateMatched": "Sun Jan 03 2021 11:07:54 GMT+0100 (West Africa Standard Time)",
        "telco": "Globacom",
        "state": "Bauchi",
        "picture": "http://placehold.it/32x32",
        "age": 77,
        "score": 84,
        "eyeColor": "brown",
        "name": "Bass Downs",
        "gender": "male",
        "phone": "+234 (832) 438-3505",
        "address": "221 Jefferson Street, Golconda, Rhode Island, 5144"
    },
    {
        "_id": "6054284cbc01b00bd8cc0f67",
        "index": 6,
        "guid": "94190afa-9f33-4295-9cf5-ebb7c4733120",
        "isActive": false,
        "isMatched": false,
        "isMigrated": false,
        "isReturned": false,
        "dateMatched": "Tue Mar 02 2021 14:50:42 GMT+0100 (West Africa Standard Time)",
        "telco": "Airtel",
        "state": "Ebonyi",
        "picture": "http://placehold.it/32x32",
        "age": 58,
        "score": 63,
        "eyeColor": "blue",
        "name": "Lewis Watson",
        "gender": "male",
        "phone": "+234 (837) 582-2723",
        "address": "336 Croton Loop, Sena, South Carolina, 6095"
    },
    {
        "_id": "6054284c73e171eca161731c",
        "index": 7,
        "guid": "7ccd720e-3895-4561-aaef-32e31a26e921",
        "isActive": true,
        "isMatched": false,
        "isMigrated": false,
        "isReturned": false,
        "dateMatched": "Wed Mar 03 2021 17:36:58 GMT+0100 (West Africa Standard Time)",
        "telco": "nineMobile",
        "state": "Borno",
        "picture": "http://placehold.it/32x32",
        "age": 54,
        "score": 94,
        "eyeColor": "green",
        "name": "Anita Fleming",
        "gender": "female",
        "phone": "+234 (986) 458-2777",
        "address": "517 Tapscott Avenue, Catharine, Colorado, 6725"
    },
    {
        "_id": "6054284ce0a8092055800e11",
        "index": 8,
        "guid": "44a87c22-d370-4de1-bb26-2732ecb74402",
        "isActive": false,
        "isMatched": true,
        "isMigrated": false,
        "isReturned": false,
        "dateMatched": "Wed Feb 17 2021 06:26:35 GMT+0100 (West Africa Standard Time)",
        "telco": "Ntel",
        "state": "Kwara",
        "picture": "http://placehold.it/32x32",
        "age": 10,
        "score": 34,
        "eyeColor": "green",
        "name": "Franks Kane",
        "gender": "male",
        "phone": "+234 (843) 473-3049",
        "address": "427 Central Avenue, Gracey, Northern Mariana Islands, 1887"
    },
    {
        "_id": "6054284c3f97f715e7141235",
        "index": 9,
        "guid": "3925a8b2-d03c-4d81-9e2c-091477b10383",
        "isActive": false,
        "isMatched": false,
        "isMigrated": false,
        "isReturned": false,
        "dateMatched": "Tue Feb 09 2021 09:41:31 GMT+0100 (West Africa Standard Time)",
        "telco": "nineMobile",
        "state": "Nasarawa",
        "picture": "http://placehold.it/32x32",
        "age": 67,
        "score": 51,
        "eyeColor": "blue",
        "name": "Gibbs Huffman",
        "gender": "male",
        "phone": "+234 (894) 541-3603",
        "address": "527 Union Street, Maury, New Hampshire, 1906"
    },
    {
        "_id": "6054284c2ba170d3253ec9c5",
        "index": 10,
        "guid": "39760052-7dd0-46ea-bf05-228ce373c3ae",
        "isActive": true,
        "isMatched": true,
        "isMigrated": false,
        "isReturned": true,
        "dateMatched": "Fri Mar 05 2021 22:22:52 GMT+0100 (West Africa Standard Time)",
        "telco": "Smile",
        "state": "Enugu",
        "picture": "http://placehold.it/32x32",
        "age": 53,
        "score": 11,
        "eyeColor": "green",
        "name": "Ada Hanson",
        "gender": "female",
        "phone": "+234 (842) 488-3649",
        "address": "710 Kimball Street, Topaz, Georgia, 5683"
    },
    {
        "_id": "6054284c5fe53bff4d91ff50",
        "index": 11,
        "guid": "6d6de620-da38-418b-8050-e7912c56cbe9",
        "isActive": true,
        "isMatched": true,
        "isMigrated": false,
        "isReturned": true,
        "dateMatched": "Fri Feb 26 2021 14:23:59 GMT+0100 (West Africa Standard Time)",
        "telco": "nineMobile",
        "state": "Cross River",
        "picture": "http://placehold.it/32x32",
        "age": 76,
        "score": 5,
        "eyeColor": "brown",
        "name": "Jensen Diaz",
        "gender": "male",
        "phone": "+234 (973) 489-3928",
        "address": "761 Greenpoint Avenue, Ernstville, Maine, 2247"
    }
]